noticeboard.py
noticeboard-0.0.1.dist-info/LICENSE
noticeboard-0.0.1.dist-info/WHEEL
noticeboard-0.0.1.dist-info/METADATA
noticeboard-0.0.1.dist-info/RECORD
