Metadata-Version: 2.1
Name: noticeboard
Version: 0.0.1
Summary: Python code for a smart noticeboard
Author-email: "John C. G. Sturdy" <jcg.sturdy@gmail.com>
Classifier: License :: OSI Approved :: GNU General Public License v3 or later (GPLv3+)
Requires-Dist: pyyaml
Requires-Dist: RPi.GPIO
Requires-Dist: picamera
